django_sitemaps.py
django_sitemaps-2.0.2.dist-info/METADATA
django_sitemaps-2.0.2.dist-info/WHEEL
django_sitemaps-2.0.2.dist-info/licenses/LICENSE
django_sitemaps-2.0.2.dist-info/RECORD
